{"match_id": "2733553", "home_team": "Forge FC", "away_team": "York United FC", "final_score": null, "match_date": "2025-10-19", "match_time": "04:00", "match_datetime": "2025-10-19 04:00", "recent_indirect_full": {"last_home": {"home": "Forge FC", "away": "Vancouver FC", "score": "1 : 1", "ah": "2", "ou": "-", "stats_rows": [{"label": "Tiros", "home": "<span style=\"color: green; font-weight: bold;\">14</span>", "away": "<span style=\"color: red;\">6</span>"}, {"label": "Tiros a Puerta", "home": "<span style=\"color: green; font-weight: bold;\">5</span>", "away": "<span style=\"color: red;\">2</span>"}, {"label": "Ataques", "home": "<span style=\"color: green; font-weight: bold;\">99</span>", "away": "<span style=\"color: red;\">67</span>"}, {"label": "Ataques Peligrosos", "home": "<span style=\"color: green; font-weight: bold;\">61</span>", "away": "<span style=\"color: red;\">14</span>"}, {"label": "Red Cards", "home": "", "away": ""}], "date": "04-10-2025", "cover_status": "NO CUBIERTO"}, "last_away": {"home": "HFX Wanderers FC", "away": "York United FC", "score": "1 : 1", "ah": "0.25", "ou": "-", "stats_rows": [{"label": "Tiros", "home": "<span style=\"color: green; font-weight: bold;\">10</span>", "away": "<span style=\"color: red;\">8</span>"}, {"label": "Tiros a Puerta", "home": "2", "away": "2"}, {"label": "Red Cards", "home": "", "away": ""}], "date": "04-10-2025", "cover_status": "indeterminado"}, "h2h_col3": {"home": "Vancouver FC", "away": "HFX Wanderers FC", "score": "3 : 1", "ah": "-", "ou": "-", "stats_rows": [{"label": "Tiros", "home": "<span style=\"color: red;\">6</span>", "away": "<span style=\"color: green; font-weight: bold;\">10</span>"}, {"label": "Tiros a Puerta", "home": "<span style=\"color: green; font-weight: bold;\">4</span>", "away": "<span style=\"color: red;\">1</span>"}, {"label": "Ataques", "home": "<span style=\"color: red;\">89</span>", "away": "<span style=\"color: green; font-weight: bold;\">112</span>"}, {"label": "Ataques Peligrosos", "home": "<span style=\"color: red;\">30</span>", "away": "<span style=\"color: green; font-weight: bold;\">39</span>"}, {"label": "Red Cards", "home": "", "away": ""}], "date": "", "cover_status": "indeterminado", "analysis": null}, "h2h_general": {"home": "York United FC", "away": "Forge FC", "score": "1 : 2", "ah": "-0.25", "ou": "-", "stats_rows": [{"label": "Tiros", "home": "<span style=\"color: red;\">10</span>", "away": "<span style=\"color: green; font-weight: bold;\">12</span>"}, {"label": "Tiros a Puerta", "home": "<span style=\"color: red;\">3</span>", "away": "<span style=\"color: green; font-weight: bold;\">7</span>"}, {"label": "Ataques", "home": "<span style=\"color: red;\">88</span>", "away": "<span style=\"color: green; font-weight: bold;\">94</span>"}, {"label": "Ataques Peligrosos", "home": "<span style=\"color: red;\">40</span>", "away": "<span style=\"color: green; font-weight: bold;\">50</span>"}, {"label": "Red Cards", "home": "", "away": ""}], "date": null, "cover_status": "CUBIERTO"}}, "comparativas_indirectas": {"left": {"title_home_name": "Forge FC", "title_away_name": "York United FC", "home_team": "Forge FC", "away_team": "HFX Wanderers FC", "score": "1 : 0", "ah": "0.75", "ou": "-", "localia": "H", "stats_rows": [{"label": "Tiros", "home": "<span style=\"color: green; font-weight: bold;\">10</span>", "away": "<span style=\"color: red;\">9</span>"}, {"label": "Tiros a Puerta", "home": "1", "away": "1"}, {"label": "Ataques", "home": "<span style=\"color: red;\">95</span>", "away": "<span style=\"color: green; font-weight: bold;\">103</span>"}, {"label": "Ataques Peligrosos", "home": "<span style=\"color: green; font-weight: bold;\">60</span>", "away": "<span style=\"color: red;\">50</span>"}, {"label": "Red Cards", "home": "", "away": ""}], "cover_status": "CUBIERTO", "analysis": "Contra este rival, Forge FC habría cubierto el handicap"}, "right": {"title_home_name": "Forge FC", "title_away_name": "York United FC", "home_team": "Vancouver FC", "away_team": "York United FC", "score": "2 : 1", "ah": "-0.5", "ou": "-", "localia": "A", "stats_rows": [{"label": "Tiros", "home": "<span style=\"color: red;\">8</span>", "away": "<span style=\"color: green; font-weight: bold;\">15</span>"}, {"label": "Tiros a Puerta", "home": "<span style=\"color: green; font-weight: bold;\">4</span>", "away": "<span style=\"color: red;\">3</span>"}, {"label": "Ataques", "home": "<span style=\"color: red;\">146</span>", "away": "<span style=\"color: green; font-weight: bold;\">195</span>"}, {"label": "Ataques Peligrosos", "home": "<span style=\"color: red;\">74</span>", "away": "<span style=\"color: green; font-weight: bold;\">121</span>"}, {"label": "Red Cards", "home": "", "away": ""}], "cover_status": "indeterminado", "analysis": "Contra este rival, el resultado para York United FC sería indeterminado"}}, "simplified_html": "<div class=\"card\"><div class=\"card-body\"><h6 class=\"card-title\">📊 Análisis Mercado vs. H2H</h6>\n            <div class=\"mb-2\">\n                <strong>Precedente (este estadio):</strong>\n                <div>Resultado: <span class=\"score-value\">2:2</span></div>\n                <div>Mov. Línea: <span class=\"ah-value\">0.75 -> 0.5</span></div>\n                <div>Cobertura AH: <span style='color: red; font-weight: bold;'>NO CUBIERTO</span></div>\n            </div>\n        <hr>\n                <div class=\"mt-2\">\n                    <strong>Precedente (H2H mǭs reciente):</strong>\n                    <div>Resultado: <span class=\"score-value\">1:2</span></div>\n                    <div>Mov. Lnea: <span class=\"ah-value\">-0.25 -> 0.5</span></div>\n                    <div>Cobertura AH: <span style='color: green; font-weight: bold;'>CUBIERTO</span></div>\n                </div>\n            </div></div>"}